<?xml version="1.0" encoding="UTF-8"?>
<jcr:root xmlns:sling="http://sling.apache.org/jcr/sling/1.0" xmlns:jcr="http://www.jcp.org/jcr/1.0" xmlns:nt="http://www.jcp.org/jcr/nt/1.0"
    jcr:primaryType="nt:unstructured"
    jcr:title="Properties"
    sling:resourceType="granite/ui/components/coral/foundation/container"
    margin="{Boolean}true">
    <items jcr:primaryType="nt:unstructured">
        <column
            jcr:primaryType="nt:unstructured"
            sling:resourceType="granite/ui/components/coral/foundation/container">
            <items jcr:primaryType="nt:unstructured">
                <image
                    jcr:primaryType="nt:unstructured"
                    sling:resourceType="granite/ui/components/coral/foundation/well">
                    <items jcr:primaryType="nt:unstructured">
                        <heading
                            jcr:primaryType="nt:unstructured"
                            sling:resourceType="granite/ui/components/coral/foundation/heading"
                            level="{Long}3"
                            text="Image Section"/>
                        <image
                            jcr:primaryType="nt:unstructured"
                            sling:resourceType="cq/gui/components/authoring/dialog/fileupload"
                            allowUpload="true"
                            autoStart="{Boolean}false"
                            class="cq-droptarget"
                            fieldDescription="Drag and Drop Image"
                            fieldLabel="Image"
                            fileNameParameter="./fileName"
                            fileReferenceParameter="./fileReference"
                            mimeTypes="[image/gif,image/jpeg,image/png,image/webp,image/tiff,image/svg+xml]"
                            multiple="{Boolean}false"
                            name="./file"
                            title="Upload Image Asset"
                            uploadUrl="${suffix.path}"
                            useHTML5="{Boolean}true"/>
                        <alttext
                            jcr:primaryType="nt:unstructured"
                            sling:resourceType="granite/ui/components/coral/foundation/form/textfield"
                            emptyText="Enter image alt text"
                            fieldDescription="Image alt text"
                            fieldLabel="Alt Text"
                            name="./imgAltText"/>
                    </items>
                </image>
                <cta
                    jcr:primaryType="nt:unstructured"
                    sling:resourceType="granite/ui/components/coral/foundation/well">
                    <items jcr:primaryType="nt:unstructured">
                        <heading
                            jcr:primaryType="nt:unstructured"
                            sling:resourceType="granite/ui/components/coral/foundation/heading"
                            level="{Long}3"
                            text="CTA Section"/>
                        <ctaLabel
                            jcr:primaryType="nt:unstructured"
                            sling:resourceType="granite/ui/components/coral/foundation/form/textfield"
                            emptyText="Enter CTA label text"
                            fieldDescription="CTA label text"
                            fieldLabel="CTA Label"
                            name="./ctaLabel"/>
                        <ctaLink
                            jcr:primaryType="nt:unstructured"
                            sling:resourceType="granite/ui/components/coral/foundation/form/pathfield"
                            emptyText="Enter CTA link"
                            fieldDescription="CTA link"
                            fieldLabel="CTA Link"
                            name="./ctaLink"
                            rootPath="/content"/>
                        <linkTarget
                            jcr:primaryType="nt:unstructured"
                            sling:resourceType="granite/ui/components/coral/foundation/form/select"
                            fieldDescription="Select new/same tab for CTA link"
                            fieldLabel="Select Link Target"
                            name="./linkTarget">
                            <items jcr:primaryType="nt:unstructured">
                                <sameTab
                                    jcr:primaryType="nt:unstructured"
                                    text="Same Tab"
                                    value="_self"/>
                                <newTab
                                    jcr:primaryType="nt:unstructured"
                                    text="New Tab"
                                    value="_blank"/>
                            </items>
                        </linkTarget>
                    </items>
                </cta>
                <card
                    jcr:primaryType="nt:unstructured"
                    sling:resourceType="granite/ui/components/coral/foundation/well">
                    <items jcr:primaryType="nt:unstructured">
                        <cardImage
                            jcr:primaryType="nt:unstructured"
                            sling:resourceType="granite/ui/components/coral/foundation/form/pathfield"
                            emptyText="Select Image"
                            fieldLabel="Card Image"
                            name="./cardImage"
                            required="{Boolean}true"
                            rootPath="/content/dam"/>
                        <alttext
                            jcr:primaryType="nt:unstructured"
                            sling:resourceType="granite/ui/components/coral/foundation/form/textfield"
                            emptyText="Enter image alt text"
                            fieldLabel="Alt Text"
                            name="./cardImgAltText"/>
                        <headerText
                            jcr:primaryType="nt:unstructured"
                            sling:resourceType="granite/ui/components/coral/foundation/form/textfield"
                            emptyText="Enter Header Text"
                            fieldLabel="Heading"
                            name="./headerText"
                            required="{Boolean}true"/>
                        <description
                            jcr:primaryType="nt:unstructured"
                            sling:resourceType="cq/gui/components/authoring/dialog/richtext"
                            fieldDescription="Character limit is 200"
                            fieldLabel="Description"
                            maxlength="200"
                            name="./cardDescription"
                            required="{Boolean}true"
                            useFixedInlineToolbar="{Boolean}true">
                            <uiSettings jcr:primaryType="nt:unstructured">
                                <cui jcr:primaryType="nt:unstructured">
                                    <inline
                                        jcr:primaryType="nt:unstructured"
                                        toolbar="[format#bold,format#italic,format#underline,#justify,#lists,links#modifylink,links#unlink,#styles,#paraformat,findreplace#find,findreplace#replace,spellcheck#checktext,misctools#specialchars,links#anchor,subsuperscript#subscript,subsuperscript#superscript,undo#redo,undo#undo,edit#cut,edit#copy,edit#paste,edit#paste-default,edit#paste-plaintext,edit#paste-wordhtml,experience-aem#colorPicker,misctools#sourceedit]">
                                        <popovers jcr:primaryType="nt:unstructured">
                                            <justify
                                                jcr:primaryType="nt:unstructured"
                                                items="[justify#justifyleft,justify#justifycenter,justify#justifyright]"
                                                ref="justify"/>
                                            <lists
                                                jcr:primaryType="nt:unstructured"
                                                items="[lists#unordered,lists#ordered,lists#outdent,lists#indent]"
                                                ref="lists"/>
                                            <paraformat
                                                jcr:primaryType="nt:unstructured"
                                                items="paraformat:getFormats:paraformat-pulldown"
                                                ref="paraformat"/>
                                            <styles
                                                jcr:primaryType="nt:unstructured"
                                                items="styles:getStyles:styles-pulldown"
                                                ref="styles"/>
                                        </popovers>
                                    </inline>
                                    <dialogFullScreen
                                        jcr:primaryType="nt:unstructured"
                                        toolbar="[format#bold,format#italic,format#underline,justify#justifyleft,justify#justifycenter,justify#justifyright,lists#unordered,lists#ordered,lists#outdent,lists#indent,links#modifylink,links#unlink,table#createoredit,#paraformat,#styles,image#imageProps,findreplace#find,findreplace#replace,undo#redo,undo#undo,subsuperscript#superscript,subsuperscript#subscript,links#anchor,spellcheck#checktext,misctools#specialchars,edit#cut,edit#copy,edit#paste-wordhtml,edit#paste-plaintext,edit#paste-default,misctools#sourceedit]">
                                        <popovers jcr:primaryType="nt:unstructured">
                                            <paraformat
                                                jcr:primaryType="nt:unstructured"
                                                items="paraformat:getFormats:paraformat-pulldown"
                                                ref="paraformat"/>
                                            <styles
                                                jcr:primaryType="nt:unstructured"
                                                items="styles:getStyles:styles-pulldown"
                                                ref="styles"/>
                                        </popovers>
                                    </dialogFullScreen>
                                    <tableEditOptions
                                        jcr:primaryType="nt:unstructured"
                                        toolbar="[table#insertcolumn-before,table#insertcolumn-after,table#removecolumn,-,table#insertrow-before,table#insertrow-after,table#removerow,-,table#mergecells-right,table#mergecells-down,table#mergecells,table#splitcell-horizontal,table#splitcell-vertical,-,table#selectrow,table#selectcolumn,-,table#ensureparagraph,-,table#modifytableandcell,table#removetable,-,undo#undo,undo#redo,-,table#exitTableEditing,-]"/>
                                </cui>
                            </uiSettings>
                            <rtePlugins jcr:primaryType="nt:unstructured">
                                <format
                                    jcr:primaryType="nt:unstructured"
                                    features="*"/>
                                <justify
                                    jcr:primaryType="nt:unstructured"
                                    features="*"/>
                                <lists
                                    jcr:primaryType="nt:unstructured"
                                    features="*"/>
                                <paraformat
                                    jcr:primaryType="nt:unstructured"
                                    features="*">
                                    <formats jcr:primaryType="nt:unstructured">
                                        <default_p
                                            jcr:primaryType="nt:unstructured"
                                            description="Paragraph"
                                            tag="p"/>
                                    </formats>
                                </paraformat>
                                <links
                                    jcr:primaryType="nt:unstructured"
                                    features="*"/>
                                <table
                                    jcr:primaryType="nt:unstructured"
                                    features="*">
                                    <hiddenHeaderConfig
                                        jcr:primaryType="nt:unstructured"
                                        hiddenHeaderClassName="cq-wcm-foundation-aria-visuallyhidden"
                                        hiddenHeaderEditingCSS="cq-RichText-hiddenHeader--editing"/>
                                </table>
                                <misctools
                                    jcr:primaryType="nt:unstructured"
                                    features="*">
                                    <specialCharsConfig jcr:primaryType="nt:unstructured">
                                        <chars jcr:primaryType="nt:unstructured">
                                            <nonbreakingspace
                                                jcr:primaryType="nt:unstructured"
                                                entity="&amp;nbsp;"
                                                name="Non-breaking space"/>
                                            <graveaccent
                                                jcr:primaryType="nt:unstructured"
                                                entity="&amp;#96;"
                                                name="Grave Accent"/>
                                            <acute
                                                jcr:primaryType="nt:unstructured"
                                                entity="&amp;acute;"
                                                name="Acute"/>
                                            <endash
                                                jcr:primaryType="nt:unstructured"
                                                entity="&amp;ndash;"
                                                name="En Dash"/>
                                            <emdash
                                                jcr:primaryType="nt:unstructured"
                                                entity="&amp;mdash;"
                                                name="Em Dash"/>
                                            <hzellipsis
                                                jcr:primaryType="nt:unstructured"
                                                entity="&amp;hellip;"
                                                name="Horizontal Ellipsis"/>
                                            <dagger
                                                jcr:primaryType="nt:unstructured"
                                                entity="&amp;dagger;"
                                                name="Dagger"/>
                                            <doubledagger
                                                jcr:primaryType="nt:unstructured"
                                                entity="&amp;Dagger;"
                                                name="Double Dagger"/>
                                            <copyright
                                                jcr:primaryType="nt:unstructured"
                                                entity="&amp;copy;"
                                                name="Copyright Sign"/>
                                            <registered_trademark
                                                jcr:primaryType="nt:unstructured"
                                                entity="&amp;reg;"
                                                name="Registered Trade Mark Sign"/>
                                            <default_trademark
                                                jcr:primaryType="nt:unstructured"
                                                entity="&amp;trade;"
                                                name="Trade Mark Sign"/>
                                            <centsign
                                                jcr:primaryType="nt:unstructured"
                                                entity="&amp;cent;"
                                                name="Cent Sign"/>
                                            <dollarsign
                                                jcr:primaryType="nt:unstructured"
                                                entity="&amp;#36;"
                                                name="Dollar Sign"/>
                                            <eurosign
                                                jcr:primaryType="nt:unstructured"
                                                entity="&amp;euro;"
                                                name="Euro Sign"/>
                                            <poundsign
                                                jcr:primaryType="nt:unstructured"
                                                entity="&amp;pound;"
                                                name="Pound Sign"/>
                                            <yensign
                                                jcr:primaryType="nt:unstructured"
                                                entity="&amp;yen;"
                                                name="Yen Sign"/>
                                            <currencysign
                                                jcr:primaryType="nt:unstructured"
                                                entity="&amp;curren;"
                                                name="Currency Sign"/>
                                            <fractiononequarter
                                                jcr:primaryType="nt:unstructured"
                                                entity="&amp;frac14;"
                                                name="Fraction one quarter"/>
                                            <fractiononehalf
                                                jcr:primaryType="nt:unstructured"
                                                entity="&amp;frac12;"
                                                name="Fraction one half"/>
                                            <fractionthreequarters
                                                jcr:primaryType="nt:unstructured"
                                                entity="&amp;frac34;"
                                                name="Fraction three quarters"/>
                                            <sup1
                                                jcr:primaryType="nt:unstructured"
                                                entity="&amp;sup1;"
                                                name="Superscript 1"/>
                                            <sup2
                                                jcr:primaryType="nt:unstructured"
                                                entity="&amp;sup2;"
                                                name="Superscript 2"/>
                                            <sup3
                                                jcr:primaryType="nt:unstructured"
                                                entity="&amp;sup3;"
                                                name="Superscript 3"/>
                                            <function
                                                jcr:primaryType="nt:unstructured"
                                                entity="&amp;fnof;"
                                                name="Function"/>
                                            <plusorminussign
                                                jcr:primaryType="nt:unstructured"
                                                entity="&amp;plusmn;"
                                                name="Plus-or-minus Sign"/>
                                            <multiplicationsign
                                                jcr:primaryType="nt:unstructured"
                                                entity="&amp;times;"
                                                name="Multiplication Sign"/>
                                            <divisionsign
                                                jcr:primaryType="nt:unstructured"
                                                entity="&amp;divide;"
                                                name="Division Sign"/>
                                            <degreesign
                                                jcr:primaryType="nt:unstructured"
                                                entity="&amp;deg;"
                                                name="Degree Sign"/>
                                            <microsign
                                                jcr:primaryType="nt:unstructured"
                                                entity="&amp;micro;"
                                                name="Micro Sign"/>
                                            <lessthanorequalto
                                                jcr:primaryType="nt:unstructured"
                                                entity="&amp;#8804;"
                                                name="Less than or equal to "/>
                                            <greaterthanorequalto
                                                jcr:primaryType="nt:unstructured"
                                                entity="&amp;#8805;"
                                                name="Greater than or equal to"/>
                                            <invertedquestionmark
                                                jcr:primaryType="nt:unstructured"
                                                entity="&amp;#191;"
                                                name="Inverted Question Mark"/>
                                            <invertedexclamation
                                                jcr:primaryType="nt:unstructured"
                                                entity="&amp;#161;"
                                                name="Inverted Exclamation"/>
                                            <loweraacute
                                                jcr:primaryType="nt:unstructured"
                                                entity="&amp;aacute;"
                                                name="Lowercase a-acute"/>
                                            <lowereacute
                                                jcr:primaryType="nt:unstructured"
                                                entity="&amp;eacute;"
                                                name="Lowercase e-acute "/>
                                            <loweriacute
                                                jcr:primaryType="nt:unstructured"
                                                entity="&amp;iacute;"
                                                name="Lowercase i-acute"/>
                                            <loweroacute
                                                jcr:primaryType="nt:unstructured"
                                                entity="&amp;oacute;"
                                                name="Lowercase o-acute"/>
                                            <loweruacute
                                                jcr:primaryType="nt:unstructured"
                                                entity="&amp;uacute;"
                                                name="Lowercase u-acute"/>
                                            <loweryacute
                                                jcr:primaryType="nt:unstructured"
                                                entity="&amp;yacute;"
                                                name="Lowercase y-acute "/>
                                            <upperaacute
                                                jcr:primaryType="nt:unstructured"
                                                entity="&amp;Aacute;"
                                                name="Uppercase a-acute"/>
                                            <uppereacute
                                                jcr:primaryType="nt:unstructured"
                                                entity="&amp;Eacute;"
                                                name="Uppercase e-acute"/>
                                            <upperiacute
                                                jcr:primaryType="nt:unstructured"
                                                entity="&amp;Iacute;"
                                                name="Uppercase i-acute"/>
                                            <upperuacute
                                                jcr:primaryType="nt:unstructured"
                                                entity="&amp;Oacute;"
                                                name="Uppercase u-acute "/>
                                            <upperoacute
                                                jcr:primaryType="nt:unstructured"
                                                entity="&amp;Oacute;"
                                                name="Uppercase o-acute"/>
                                            <upperyacute
                                                jcr:primaryType="nt:unstructured"
                                                entity="&amp;Yacute;"
                                                name="Uppercase y-acute"/>
                                            <emul
                                                jcr:primaryType="nt:unstructured"
                                                entity="&amp;euml;"
                                                name="Lowercase e diaeresis"/>
                                            <imul
                                                jcr:primaryType="nt:unstructured"
                                                entity="&amp;iuml;"
                                                name="Lowercase i diaeresis"/>
                                            <omul
                                                jcr:primaryType="nt:unstructured"
                                                entity="&amp;ouml;"
                                                name="Lowercase o diaeresis"/>
                                            <umul
                                                jcr:primaryType="nt:unstructured"
                                                entity="&amp;uuml;"
                                                name="Lowercase u diaeresis"/>
                                            <ymul
                                                jcr:primaryType="nt:unstructured"
                                                entity="&amp;yuml;"
                                                name="Lowercase y diaeresis "/>
                                            <Amul
                                                jcr:primaryType="nt:unstructured"
                                                entity="&amp;Auml;"
                                                name="Uppercase a diaeresis"/>
                                            <Emul
                                                jcr:primaryType="nt:unstructured"
                                                entity="&amp;Euml;"
                                                name="Uppercase e diaeresis"/>
                                            <Imul
                                                jcr:primaryType="nt:unstructured"
                                                entity="&amp;Iuml;"
                                                name="Uppercase i diaeresis"/>
                                            <Omul
                                                jcr:primaryType="nt:unstructured"
                                                entity="&amp;Ouml;"
                                                name="Uppercase o diaeresis"/>
                                            <Umul
                                                jcr:primaryType="nt:unstructured"
                                                entity="&amp;Uuml;"
                                                name="Uppercase u diaeresis"/>
                                            <Ymul
                                                jcr:primaryType="nt:unstructured"
                                                entity="&amp;Yuml;"
                                                name="Uppercase y diaeresis"/>
                                            <atilde
                                                jcr:primaryType="nt:unstructured"
                                                entity="&amp;atilde;"
                                                name="Lowercase a tilde"/>
                                            <ntilde
                                                jcr:primaryType="nt:unstructured"
                                                entity="&amp;ntilde;"
                                                name="Lowercase n tilde"/>
                                            <otilde
                                                jcr:primaryType="nt:unstructured"
                                                entity="&amp;otilde;"
                                                name=" Lowercase o tilde"/>
                                            <Atilde
                                                jcr:primaryType="nt:unstructured"
                                                entity="&amp;Atilde;"
                                                name="Uppercase a tilde"/>
                                            <Ntilde
                                                jcr:primaryType="nt:unstructured"
                                                entity="&amp;Ntilde;"
                                                name="Uppercase n tilde"/>
                                            <Otilde
                                                jcr:primaryType="nt:unstructured"
                                                entity="&amp;Otilde;"
                                                name="Uppercase o tilde"/>
                                            <Alpha
                                                jcr:primaryType="nt:unstructured"
                                                entity="&amp;Alpha;"
                                                name="Uppercase alpha"/>
                                            <Beta
                                                jcr:primaryType="nt:unstructured"
                                                entity="&amp;Beta;"
                                                name="Uppercase beta "/>
                                            <Gamma
                                                jcr:primaryType="nt:unstructured"
                                                entity="&amp;Gamma;"
                                                name="Uppercase gamma "/>
                                            <Delta
                                                jcr:primaryType="nt:unstructured"
                                                entity="&amp;Delta;"
                                                name="Uppercase delta"/>
                                            <Epsilon
                                                jcr:primaryType="nt:unstructured"
                                                entity="&amp;Epsilon;"
                                                name="Uppercase epsilon"/>
                                            <Zeta
                                                jcr:primaryType="nt:unstructured"
                                                entity="&amp;Zeta;"
                                                name="Uppercase zeta"/>
                                            <Eta
                                                jcr:primaryType="nt:unstructured"
                                                entity="&amp;Eta;"
                                                name="Uppercase eta"/>
                                            <Theta
                                                jcr:primaryType="nt:unstructured"
                                                entity="&amp;Theta;"
                                                name="Uppercase theta"/>
                                            <Iota
                                                jcr:primaryType="nt:unstructured"
                                                entity="&amp;Iota;"
                                                name="Uppercase iota"/>
                                            <Kappa
                                                jcr:primaryType="nt:unstructured"
                                                entity="&amp;Kappa;"
                                                name="Uppercase kappa"/>
                                            <Lambda
                                                jcr:primaryType="nt:unstructured"
                                                entity="&amp;Lambda;"
                                                name="Uppercase lambda"/>
                                            <Mu
                                                jcr:primaryType="nt:unstructured"
                                                entity="&amp;Mu;"
                                                name="Uppercase mu"/>
                                            <Nu
                                                jcr:primaryType="nt:unstructured"
                                                entity="&amp;Nu;"
                                                name="Uppercase nu"/>
                                            <Xi
                                                jcr:primaryType="nt:unstructured"
                                                entity="&amp;Xi;"
                                                name="Uppercase xi"/>
                                            <Omicron
                                                jcr:primaryType="nt:unstructured"
                                                entity="&amp;Omicron;"
                                                name="Uppercase omicron"/>
                                            <Pi
                                                jcr:primaryType="nt:unstructured"
                                                entity="&amp;Pi;"
                                                name="Uppercase pi"/>
                                            <Rho
                                                jcr:primaryType="nt:unstructured"
                                                entity="&amp;Sigma;"
                                                name="Uppercase rho"/>
                                            <Sigma
                                                jcr:primaryType="nt:unstructured"
                                                entity="&amp;Sigma;"
                                                name="Uppercase sigma"/>
                                            <Tau
                                                jcr:primaryType="nt:unstructured"
                                                entity="&amp;Tau;"
                                                name="Uppercase tau"/>
                                            <Upsilon
                                                jcr:primaryType="nt:unstructured"
                                                entity="&amp;Upsilon;"
                                                name="Uppercase upsilon"/>
                                            <Phi
                                                jcr:primaryType="nt:unstructured"
                                                entity="&amp;Phi;"
                                                name="Uppercase phi "/>
                                            <Chi
                                                jcr:primaryType="nt:unstructured"
                                                entity="&amp;Chi;"
                                                name="Uppercase chi"/>
                                            <Psi
                                                jcr:primaryType="nt:unstructured"
                                                entity="&amp;Psi;"
                                                name="Uppercase psi"/>
                                            <Omega
                                                jcr:primaryType="nt:unstructured"
                                                entity="&amp;Omega;"
                                                name="Uppercase omega"/>
                                            <alpha
                                                jcr:primaryType="nt:unstructured"
                                                entity="&amp;alpha;"
                                                name="Lowercase alpha"/>
                                            <beta
                                                jcr:primaryType="nt:unstructured"
                                                entity="&amp;beta;"
                                                name="Lowercase beta"/>
                                            <gamma
                                                jcr:primaryType="nt:unstructured"
                                                entity="&amp;gamma;"
                                                name="Lowercase gamma"/>
                                            <delta
                                                jcr:primaryType="nt:unstructured"
                                                entity="&amp;delta;"
                                                name="Lowercase delta"/>
                                            <epsilon
                                                jcr:primaryType="nt:unstructured"
                                                entity="&amp;epsilon;"
                                                name="Lowercase epsilon"/>
                                            <zeta
                                                jcr:primaryType="nt:unstructured"
                                                entity="&amp;zeta;"
                                                name="Lowercase zeta"/>
                                            <eta
                                                jcr:primaryType="nt:unstructured"
                                                entity="&amp;eta;"
                                                name="Lowercase eta"/>
                                            <theta
                                                jcr:primaryType="nt:unstructured"
                                                entity="&amp;theta;"
                                                name="Lowercase theta"/>
                                            <iota
                                                jcr:primaryType="nt:unstructured"
                                                entity="&amp;iota;"
                                                name="Lowercase iota"/>
                                            <kappa
                                                jcr:primaryType="nt:unstructured"
                                                entity="&amp;kappa;"
                                                name="Lowercase kappa"/>
                                            <lambda
                                                jcr:primaryType="nt:unstructured"
                                                entity="&amp;lambda;"
                                                name="Lowercase lambda"/>
                                            <mu
                                                jcr:primaryType="nt:unstructured"
                                                entity="&amp;mu;"
                                                name="Lowercase mu"/>
                                            <nu
                                                jcr:primaryType="nt:unstructured"
                                                entity="&amp;nu;"
                                                name="Lowercase nu"/>
                                            <zi
                                                jcr:primaryType="nt:unstructured"
                                                entity="&amp;xi;"
                                                name="Lowercase zi"/>
                                            <omicron
                                                jcr:primaryType="nt:unstructured"
                                                entity="&amp;omicron;"
                                                name="Lowercase omicron"/>
                                            <pi
                                                jcr:primaryType="nt:unstructured"
                                                entity="&amp;pi;"
                                                name="Lowercase pi"/>
                                            <rho
                                                jcr:primaryType="nt:unstructured"
                                                entity="&amp;rho;"
                                                name="Lowercase rho"/>
                                            <fsigma
                                                jcr:primaryType="nt:unstructured"
                                                entity="&amp;sigmaf;"
                                                name="Lowercase final sigma"/>
                                            <sigma
                                                jcr:primaryType="nt:unstructured"
                                                entity="&amp;sigma;"
                                                name="Lowecase sigma"/>
                                            <tau
                                                jcr:primaryType="nt:unstructured"
                                                entity="&amp;tau;"
                                                name="Lowercase tau"/>
                                            <upsilon
                                                jcr:primaryType="nt:unstructured"
                                                entity="&amp;upsilon;"
                                                name="Lowercase upsilon"/>
                                            <phi
                                                jcr:primaryType="nt:unstructured"
                                                entity="&amp;phi;"
                                                name="Lowercase phi"/>
                                            <chi
                                                jcr:primaryType="nt:unstructured"
                                                entity="&amp;chi;"
                                                name="Lowercase chi"/>
                                            <psi
                                                jcr:primaryType="nt:unstructured"
                                                entity="&amp;psi;"
                                                name="Lowercase psi"/>
                                            <omega
                                                jcr:primaryType="nt:unstructured"
                                                entity="&amp;omega;"
                                                name="Lowercase omega"/>
                                            <thetasym
                                                jcr:primaryType="nt:unstructured"
                                                entity="&amp;thetasym;"
                                                name="Greek Theta"/>
                                            <upsih
                                                jcr:primaryType="nt:unstructured"
                                                entity="&amp;upsih;"
                                                name="Greek Upsilon with Hook"/>
                                            <piv
                                                jcr:primaryType="nt:unstructured"
                                                entity="&amp;piv;"
                                                name="Greek Pi"/>
                                        </chars>
                                    </specialCharsConfig>
                                </misctools>
                                <findreplace
                                    jcr:primaryType="nt:unstructured"
                                    features="*"/>
                                <keys
                                    jcr:primaryType="nt:unstructured"
                                    tabSize="3"/>
                                <image
                                    jcr:primaryType="nt:unstructured"
                                    features="*"/>
                                <edit
                                    jcr:primaryType="nt:unstructured"
                                    features="*"/>
                                <undo
                                    jcr:primaryType="nt:unstructured"
                                    features="*"/>
                                <subsuperscript
                                    jcr:primaryType="nt:unstructured"
                                    features="*"/>
                                <tracklinks
                                    jcr:primaryType="nt:unstructured"
                                    features="*"/>
                                <spellcheck
                                    jcr:primaryType="nt:unstructured"
                                    features="*"/>
                            </rtePlugins>
                            <htmlRules jcr:primaryType="nt:unstructured">
                                <docType jcr:primaryType="nt:unstructured">
                                    <typeConfig
                                        jcr:primaryType="nt:unstructured"
                                        useSemanticMarkup="{Boolean}true">
                                        <semanticMarkupMap
                                            jcr:primaryType="nt:unstructured"
                                            b="strong"
                                            i="em"/>
                                    </typeConfig>
                                </docType>
                            </htmlRules>
                        </description>
                        <ctaLabel
                            jcr:primaryType="nt:unstructured"
                            sling:resourceType="granite/ui/components/coral/foundation/form/textfield"
                            emptyText="Enter CTA label text"
                            fieldLabel="CTA Label"
                            name="./cardCtaLabel"/>
                        <ctaLink
                            jcr:primaryType="nt:unstructured"
                            sling:resourceType="granite/ui/components/coral/foundation/form/pathfield"
                            emptyText="Enter CTA link"
                            fieldLabel="CTA Link"
                            name="./cardCtaLink"
                            rootPath="/content"/>
                        <linkTarget
                            jcr:primaryType="nt:unstructured"
                            sling:resourceType="granite/ui/components/coral/foundation/form/select"
                            fieldLabel="CTA Link Target"
                            name="./cardLinkTarget">
                            <items jcr:primaryType="nt:unstructured">
                                <sameTab
                                    jcr:primaryType="nt:unstructured"
                                    text="Same Tab"
                                    value="_self"/>
                                <newTab
                                    jcr:primaryType="nt:unstructured"
                                    text="New Tab"
                                    value="_blank"/>
                            </items>
                        </linkTarget>
                        <ctaAnalytics
                            jcr:primaryType="nt:unstructured"
                            sling:resourceType="granite/ui/components/coral/foundation/form/textfield"
                            emptyText="Enter Analytics Tag"
                            fieldLabel="CTA Analytics"
                            name="./ctaAnalytics"/>
                    </items>
                </card>
            </items>
        </column>
    </items>
</jcr:root>
